{"2023-08-21T00Z": {"BEGU": true, "CREU": true, "ROSE": true}, "2023-08-21T01Z": {"BEGU": true, "CREU": true, "ROSE": true}, "2023-08-21T02Z": {"BEGU": true, "CREU": true, "ROSE": true}, "2023-08-21T03Z": {"BEGU": true, "CREU": true, "ROSE": true}, "2023-08-21T04Z": {"BEGU": true, "CREU": true, "ROSE": true}, "2023-08-21T05Z": {"BEGU": true, "CREU": true, "ROSE": true}, "2023-08-21T06Z": {"BEGU": true, "CREU": true, "ROSE": true}, "2023-08-21T07Z": {"BEGU": true, "CREU": true, "ROSE": true}, "2023-08-21T08Z": {"BEGU": true, "CREU": true, "ROSE": true}, "2023-08-21T09Z": {"BEGU": true, "CREU": true, "ROSE": true}, "2023-08-21T10Z": {"BEGU": true, "CREU": true, "ROSE": true}, "2023-08-21T11Z": {"BEGU": true, "CREU": true, "ROSE": true}, "2023-08-21T12Z": {"BEGU": true, "CREU": true, "ROSE": true}, "2023-08-21T13Z": {"BEGU": true, "CREU": true, "ROSE": true}, "2023-08-21T14Z": {"BEGU": true, "CREU": true, "ROSE": true}, "2023-08-21T15Z": {"BEGU": true, "CREU": true, "ROSE": true}, "2023-08-21T16Z": {"BEGU": true, "CREU": true, "ROSE": true}, "2023-08-21T17Z": {"BEGU": true, "CREU": true, "ROSE": true}, "2023-08-21T18Z": {"BEGU": true, "CREU": true, "ROSE": true}, "2023-08-21T19Z": {"BEGU": true, "CREU": true, "ROSE": true}, "2023-08-21T20Z": {"BEGU": true, "CREU": true, "ROSE": true}, "2023-08-21T21Z": {"BEGU": true, "CREU": true, "ROSE": true}, "2023-08-21T22Z": {"BEGU": true, "CREU": true, "ROSE": true}, "2023-08-21T23Z": {"BEGU": true, "CREU": true, "ROSE": true}, "2023-08-22T00Z": {"BEGU": true, "CREU": true, "ROSE": true}, "2023-08-22T01Z": {"BEGU": true, "CREU": true, "ROSE": true}, "2023-08-22T02Z": {"BEGU": true, "CREU": true, "ROSE": true}, "2023-08-22T03Z": {"BEGU": true, "CREU": true, "ROSE": true}, "2023-08-22T04Z": {"BEGU": true, "CREU": true, "ROSE": true}, "2023-08-22T05Z": {"BEGU": true, "CREU": true, "ROSE": true}, "2023-08-22T06Z": {"BEGU": true, "CREU": true, "ROSE": true}, "2023-08-22T07Z": {"BEGU": true, "CREU": true, "ROSE": true}, "2023-08-22T08Z": {"BEGU": true, "CREU": true, "ROSE": true}, "2023-08-22T09Z": {"BEGU": true, "CREU": true, "ROSE": true}, "2023-08-22T10Z": {"BEGU": true, "CREU": true, "ROSE": true}, "2023-08-22T11Z": {"BEGU": true, "CREU": true, "ROSE": true}, "2023-08-22T12Z": {"BEGU": true, "CREU": true, "ROSE": true}, "2023-08-22T13Z": {"BEGU": true, "CREU": true, "ROSE": true}, "2023-08-22T14Z": {"BEGU": true, "CREU": true, "ROSE": true}, "2023-08-22T15Z": {"BEGU": true, "CREU": true, "ROSE": true}, "2023-08-22T16Z": {"BEGU": true, "CREU": true, "ROSE": true}, "2023-08-22T17Z": {"BEGU": true, "CREU": true, "ROSE": true}, "2023-08-22T18Z": {"BEGU": true, "CREU": true, "ROSE": true}, "2023-08-22T19Z": {"BEGU": true, "CREU": true, "ROSE": true}, "2023-08-22T20Z": {"BEGU": true, "CREU": true, "ROSE": true}, "2023-08-22T21Z": {"BEGU": true, "CREU": true, "ROSE": true}, "2023-08-22T22Z": {"BEGU": true, "CREU": true, "ROSE": true}, "2023-08-22T23Z": {"BEGU": true, "CREU": true, "ROSE": true}, "2023-08-23T00Z": {"BEGU": true, "CREU": true, "ROSE": true}, "2023-08-23T01Z": {"BEGU": true, "CREU": true, "ROSE": true}, "2023-08-23T02Z": {"BEGU": true, "CREU": true, "ROSE": true}, "2023-08-23T03Z": {"BEGU": true, "CREU": true, "ROSE": true}, "2023-08-23T04Z": {"BEGU": true, "CREU": true, "ROSE": true}, "2023-08-23T05Z": {"BEGU": true, "CREU": true, "ROSE": true}, "2023-08-23T06Z": {"BEGU": true, "CREU": true, "ROSE": true}, "2023-08-23T07Z": {"BEGU": true, "CREU": true, "ROSE": true}, "2023-08-23T08Z": {"BEGU": true, "CREU": true, "ROSE": true}, "2023-08-23T09Z": {"BEGU": true, "CREU": true, "ROSE": true}, "2023-08-23T10Z": {"BEGU": true, "CREU": true, "ROSE": true}, "2023-08-23T11Z": {"BEGU": true, "CREU": true, "ROSE": true}, "2023-08-23T12Z": {"BEGU": true, "CREU": true, "ROSE": true}, "2023-08-23T13Z": {"BEGU": true, "CREU": true, "ROSE": true}, "2023-08-23T14Z": {"BEGU": true, "CREU": true, "ROSE": true}, "2023-08-23T15Z": {"BEGU": true, "CREU": true, "ROSE": true}, "2023-08-23T16Z": {"BEGU": true, "CREU": true, "ROSE": true}, "2023-08-23T17Z": {"BEGU": true, "CREU": true, "ROSE": true}, "2023-08-23T18Z": {"BEGU": true, "CREU": true, "ROSE": true}, "2023-08-23T19Z": {"BEGU": true, "CREU": true, "ROSE": true}, "2023-08-23T20Z": {"BEGU": true, "CREU": true, "ROSE": true}, "2023-08-23T21Z": {"BEGU": true, "CREU": true, "ROSE": true}, "2023-08-23T22Z": {"BEGU": true, "CREU": true, "ROSE": true}, "2023-08-23T23Z": {"BEGU": true, "CREU": true, "ROSE": true}, "2023-08-24T00Z": {"BEGU": true, "CREU": true, "ROSE": true}, "2023-08-24T01Z": {"BEGU": true, "CREU": true, "ROSE": true}, "2023-08-24T02Z": {"BEGU": true, "CREU": true, "ROSE": true}, "2023-08-24T03Z": {"BEGU": true, "CREU": true, "ROSE": true}, "2023-08-24T04Z": {"BEGU": true, "CREU": true, "ROSE": true}, "2023-08-24T05Z": {"BEGU": true, "CREU": true, "ROSE": true}, "2023-08-24T06Z": {"BEGU": true, "CREU": true, "ROSE": true}, "2023-08-24T07Z": {"BEGU": true, "CREU": true, "ROSE": true}, "2023-08-24T08Z": {"BEGU": true, "CREU": true, "ROSE": true}, "2023-08-24T09Z": {"BEGU": true, "CREU": true, "ROSE": true}, "2023-08-24T10Z": {"BEGU": true, "CREU": true, "ROSE": true}, "2023-08-24T11Z": {"BEGU": true, "CREU": true, "ROSE": true}, "2023-08-24T12Z": {"BEGU": true, "CREU": true, "ROSE": true}, "2023-08-24T13Z": {"BEGU": true, "CREU": true, "ROSE": true}, "2023-08-24T14Z": {"BEGU": true, "CREU": true, "ROSE": true}, "2023-08-24T15Z": {"BEGU": true, "CREU": true, "ROSE": true}, "2023-08-24T16Z": {"BEGU": true, "CREU": true, "ROSE": true}, "2023-08-24T17Z": {"BEGU": true, "CREU": true, "ROSE": true}, "2023-08-24T18Z": {"BEGU": true, "CREU": true, "ROSE": true}, "2023-08-24T19Z": {"BEGU": true, "CREU": true, "ROSE": true}, "2023-08-24T20Z": {"BEGU": true, "CREU": true, "ROSE": true}, "2023-08-24T21Z": {"BEGU": true, "CREU": true, "ROSE": true}, "2023-08-24T22Z": {"BEGU": true, "CREU": true, "ROSE": true}, "2023-08-24T23Z": {"BEGU": true, "CREU": true, "ROSE": true}, "2023-08-25T00Z": {"BEGU": true, "CREU": true, "ROSE": true}, "2023-08-25T01Z": {"BEGU": true, "CREU": true, "ROSE": true}, "2023-08-25T02Z": {"BEGU": true, "CREU": true, "ROSE": true}, "2023-08-25T03Z": {"BEGU": true, "CREU": true, "ROSE": true}, "2023-08-25T04Z": {"BEGU": true, "CREU": true, "ROSE": true}, "2023-08-25T05Z": {"BEGU": true, "CREU": true, "ROSE": true}, "2023-08-25T06Z": {"BEGU": true, "CREU": true, "ROSE": true}, "2023-08-25T07Z": {"BEGU": true, "CREU": true, "ROSE": true}, "2023-08-25T08Z": {"BEGU": true, "CREU": true, "ROSE": true}, "2023-08-25T09Z": {"BEGU": true, "CREU": true, "ROSE": true}, "2023-08-25T10Z": {"BEGU": true, "CREU": true, "ROSE": true}, "2023-08-25T11Z": {"BEGU": true, "CREU": true, "ROSE": true}, "2023-08-25T12Z": {"BEGU": true, "CREU": true, "ROSE": true}, "2023-08-25T13Z": {"BEGU": true, "CREU": true, "ROSE": true}, "2023-08-25T14Z": {"BEGU": true, "CREU": true, "ROSE": true}, "2023-08-25T15Z": {"BEGU": true, "CREU": true, "ROSE": true}, "2023-08-25T16Z": {"BEGU": true, "CREU": true, "ROSE": true}, "2023-08-25T17Z": {"BEGU": true, "CREU": true, "ROSE": true}, "2023-08-25T18Z": {"BEGU": true, "CREU": true, "ROSE": true}, "2023-08-25T19Z": {"BEGU": true, "CREU": true, "ROSE": true}, "2023-08-25T20Z": {"BEGU": true, "CREU": true, "ROSE": true}, "2023-08-25T21Z": {"BEGU": true, "CREU": true, "ROSE": true}, "2023-08-25T22Z": {"BEGU": true, "CREU": true, "ROSE": true}, "2023-08-25T23Z": {"BEGU": true, "CREU": true, "ROSE": true}, "2023-08-28T14Z": {"BEGU": true, "CREU": true, "ROSE": true}, "2023-08-28T15Z": {"BEGU": true, "CREU": true, "ROSE": true}, "2023-08-28T16Z": {"BEGU": true, "CREU": true, "ROSE": true}, "2023-08-28T17Z": {"BEGU": true, "CREU": true, "ROSE": true}, "2023-08-28T18Z": {"BEGU": true, "CREU": true, "ROSE": true}, "2023-08-28T19Z": {"BEGU": true, "CREU": true, "ROSE": true}, "2023-08-28T20Z": {"BEGU": true, "CREU": true, "ROSE": true}, "2023-08-28T21Z": {"BEGU": true, "CREU": true, "ROSE": true}, "2023-08-28T22Z": {"BEGU": true, "CREU": true, "ROSE": true}, "2023-08-28T23Z": {"BEGU": true, "CREU": true, "ROSE": true}, "2023-08-29T00Z": {"BEGU": true, "CREU": true, "ROSE": true}, "2023-08-29T01Z": {"BEGU": true, "CREU": true, "ROSE": true}, "2023-08-29T02Z": {"BEGU": true, "CREU": true, "ROSE": true}, "2023-08-29T03Z": {"BEGU": true}, "2023-08-29T04Z": {"BEGU": true}, "2023-08-29T05Z": {"BEGU": true, "ROSE": true}, "2023-08-29T06Z": {"BEGU": true, "CREU": true, "ROSE": true}, "2023-08-29T07Z": {"BEGU": true, "CREU": true, "ROSE": true}, "2023-08-29T08Z": {"BEGU": true, "CREU": true, "ROSE": true}, "2023-08-29T09Z": {"BEGU": true, "CREU": true, "ROSE": true}, "2023-08-29T10Z": {"BEGU": true, "CREU": true, "ROSE": true}, "2023-08-29T11Z": {"BEGU": true, "CREU": true, "ROSE": true}, "2023-08-29T12Z": {"BEGU": true, "CREU": true, "ROSE": true}, "2023-08-29T13Z": {"BEGU": true, "CREU": true, "ROSE": true}, "2023-08-29T14Z": {"BEGU": true, "CREU": true, "ROSE": true}, "2023-08-29T15Z": {"BEGU": true, "CREU": true, "ROSE": true}, "2023-08-29T16Z": {"BEGU": true}, "2023-08-29T17Z": {"BEGU": true}, "2023-08-29T18Z": {"BEGU": true}, "2023-08-29T19Z": {"BEGU": true}, "2023-08-29T20Z": {"BEGU": true}, "2023-08-29T21Z": {"BEGU": true}, "2023-08-29T22Z": {"BEGU": true}, "2023-08-29T23Z": {"BEGU": true}, "2023-08-30T00Z": {"BEGU": true}, "2023-08-30T01Z": {"BEGU": true}, "2023-08-30T02Z": {"BEGU": true}, "2023-08-30T03Z": {"BEGU": true}, "2023-08-30T04Z": {"BEGU": true}, "2023-08-30T05Z": {"BEGU": true}, "2023-08-30T06Z": {"BEGU": true}, "2023-08-30T07Z": {"BEGU": true}, "2023-08-30T08Z": {"BEGU": true}, "2023-08-30T09Z": {"BEGU": true}, "2023-08-30T10Z": {"BEGU": true}, "2023-08-30T11Z": {"BEGU": true}, "2023-08-30T12Z": {"BEGU": true}, "2023-08-30T13Z": {"BEGU": true}, "2023-08-30T14Z": {"BEGU": true}, "2023-08-30T15Z": {"BEGU": true}, "2023-08-30T16Z": {"BEGU": true}, "2023-08-30T17Z": {"BEGU": true}, "2023-08-30T18Z": {"BEGU": true}, "2023-08-30T19Z": {"BEGU": true}, "2023-08-30T20Z": {"BEGU": true, "CREU": true, "ROSE": true}, "2023-08-30T21Z": {"BEGU": true, "CREU": true, "ROSE": true}, "2023-08-30T22Z": {"BEGU": true, "CREU": true, "ROSE": true}, "2023-08-30T23Z": {"BEGU": true}, "2023-08-31T00Z": {"BEGU": true}, "2023-08-31T01Z": {"BEGU": true}, "2023-08-31T02Z": {"BEGU": true}, "2023-08-31T03Z": {"BEGU": true}, "2023-08-31T04Z": {"BEGU": true}, "2023-08-31T05Z": {"BEGU": true}, "2023-08-31T06Z": {"BEGU": true}, "2023-08-31T07Z": {"BEGU": true}, "2023-08-31T08Z": {"BEGU": true}, "2023-08-31T09Z": {"BEGU": true}, "2023-08-31T10Z": {"BEGU": true}, "2023-08-31T11Z": {"BEGU": true}, "2023-08-31T12Z": {"BEGU": true, "CREU": true, "ROSE": true}, "2023-08-31T13Z": {"BEGU": true, "CREU": true, "ROSE": true}, "2023-08-31T14Z": {"BEGU": true, "CREU": true, "ROSE": true}, "2023-08-31T15Z": {"BEGU": true, "CREU": true, "ROSE": true}, "2023-08-31T16Z": {"BEGU": true, "CREU": true, "ROSE": true}, "2023-08-31T17Z": {"BEGU": true, "CREU": true, "ROSE": true}, "2023-08-31T18Z": {"BEGU": true, "CREU": true, "ROSE": true}, "2023-08-31T19Z": {"BEGU": true, "CREU": true, "ROSE": true}, "2023-08-31T20Z": {"BEGU": true, "CREU": true, "ROSE": true}, "2023-08-31T21Z": {"BEGU": true, "CREU": true, "ROSE": true}, "2023-08-31T22Z": {"BEGU": true, "CREU": true, "ROSE": true}, "2023-08-31T23Z": {"BEGU": true, "CREU": true, "ROSE": true}, "2023-09-01T00Z": {"BEGU": true, "CREU": true, "ROSE": true}, "2023-09-01T01Z": {"BEGU": true, "CREU": true, "ROSE": true}, "2023-09-01T02Z": {"BEGU": true, "CREU": true, "ROSE": true}, "2023-09-01T03Z": {"BEGU": true, "CREU": true, "ROSE": true}, "2023-09-01T04Z": {"BEGU": true, "CREU": true, "ROSE": true}, "2023-09-01T05Z": {"BEGU": true, "CREU": true, "ROSE": true}, "2023-09-01T06Z": {"BEGU": true, "CREU": true, "ROSE": true}, "2023-09-01T07Z": {"BEGU": true, "CREU": true, "ROSE": true}, "2023-09-01T08Z": {"BEGU": true, "CREU": true, "ROSE": true}, "2023-09-01T09Z": {"BEGU": true, "CREU": true, "ROSE": true}, "2023-09-01T10Z": {"BEGU": true, "CREU": true, "ROSE": true}, "2023-09-01T11Z": {"BEGU": true, "CREU": true, "ROSE": true}, "2023-09-01T12Z": {"BEGU": true, "CREU": true, "ROSE": true}, "2023-09-01T13Z": {"BEGU": true, "CREU": true, "ROSE": true}, "2023-09-01T14Z": {"BEGU": true, "CREU": true, "ROSE": true}, "2023-09-01T15Z": {"BEGU": true, "CREU": true, "ROSE": true}, "2023-09-01T16Z": {"BEGU": true, "CREU": true, "ROSE": true}, "2023-09-01T17Z": {"BEGU": true, "CREU": true, "ROSE": true}, "2023-09-01T18Z": {"BEGU": true, "CREU": true, "ROSE": true}, "2023-09-01T19Z": {"BEGU": true, "CREU": true, "ROSE": true}, "2023-09-01T20Z": {"BEGU": true, "CREU": true, "ROSE": true}, "2023-09-01T21Z": {"BEGU": true, "CREU": true, "ROSE": true}, "2023-09-01T22Z": {"BEGU": true, "CREU": true, "ROSE": true}, "2023-09-01T23Z": {"BEGU": true, "CREU": true, "ROSE": true}, "2023-09-02T00Z": {"BEGU": true, "CREU": true, "ROSE": true}, "2023-09-02T01Z": {"BEGU": true, "CREU": true, "ROSE": true}, "2023-09-02T02Z": {"BEGU": true, "CREU": true, "ROSE": true}, "2023-09-02T03Z": {"BEGU": true, "CREU": true, "ROSE": true}, "2023-09-02T04Z": {"BEGU": true, "CREU": true, "ROSE": true}, "2023-09-02T05Z": {"BEGU": true, "CREU": true, "ROSE": true}, "2023-09-02T06Z": {"BEGU": true, "CREU": true, "ROSE": true}, "2023-09-02T07Z": {"BEGU": true, "CREU": true, "ROSE": true}, "2023-09-02T08Z": {"BEGU": true, "CREU": true, "ROSE": true}, "2023-09-02T09Z": {"BEGU": true, "CREU": true, "ROSE": true}, "2023-09-02T10Z": {"BEGU": true, "CREU": true, "ROSE": true}, "2023-09-02T11Z": {"BEGU": true, "CREU": true, "ROSE": true}, "2023-09-02T12Z": {"BEGU": true, "CREU": true, "ROSE": true}, "2023-09-02T13Z": {"BEGU": true, "CREU": true, "ROSE": true}, "2023-09-02T14Z": {"BEGU": true, "CREU": true, "ROSE": true}, "2023-09-02T15Z": {"BEGU": true, "CREU": true, "ROSE": true}, "2023-09-02T16Z": {"BEGU": true, "CREU": true, "ROSE": true}, "2023-09-02T17Z": {"BEGU": true, "CREU": true, "ROSE": true}, "2023-09-02T18Z": {"BEGU": true, "CREU": true, "ROSE": true}, "2023-09-02T19Z": {"BEGU": true, "CREU": true, "ROSE": true}, "2023-09-02T20Z": {"BEGU": true, "CREU": true, "ROSE": true}, "2023-09-02T21Z": {"BEGU": true, "CREU": true, "ROSE": true}, "2023-09-02T22Z": {"BEGU": true, "CREU": true, "ROSE": true}, "2023-09-02T23Z": {"BEGU": true, "CREU": true, "ROSE": true}, "2023-09-03T00Z": {"BEGU": true, "CREU": true, "ROSE": true}, "2023-09-03T01Z": {"BEGU": true, "CREU": true, "ROSE": true}, "2023-09-03T02Z": {"BEGU": true, "CREU": true, "ROSE": true}, "2023-09-03T03Z": {"BEGU": true, "CREU": true, "ROSE": true}, "2023-09-03T04Z": {"BEGU": true, "CREU": true, "ROSE": true}, "2023-09-03T05Z": {"BEGU": true, "CREU": true, "ROSE": true}, "2023-09-03T06Z": {"BEGU": true, "CREU": true, "ROSE": true}, "2023-09-03T07Z": {"BEGU": true, "CREU": true, "ROSE": true}, "2023-09-03T08Z": {"BEGU": true, "CREU": true, "ROSE": true}, "2023-09-03T09Z": {"BEGU": true, "CREU": true, "ROSE": true}, "2023-09-03T10Z": {"BEGU": true, "CREU": true, "ROSE": true}, "2023-09-03T11Z": {"BEGU": true, "CREU": true, "ROSE": true}, "2023-09-03T12Z": {"BEGU": true, "CREU": true, "ROSE": true}, "2023-09-03T13Z": {"BEGU": true, "CREU": true, "ROSE": true}, "2023-09-03T14Z": {"BEGU": true, "CREU": true, "ROSE": true}, "2023-09-03T15Z": {"BEGU": true, "CREU": true, "ROSE": true}, "2023-09-03T16Z": {"BEGU": true, "CREU": true, "ROSE": true}, "2023-09-03T17Z": {"BEGU": true, "CREU": true, "ROSE": true}, "2023-09-03T18Z": {"BEGU": true, "CREU": true, "ROSE": true}, "2023-09-03T19Z": {"BEGU": true, "CREU": true, "ROSE": true}, "2023-09-03T20Z": {"BEGU": true, "CREU": true, "ROSE": true}, "2023-09-03T21Z": {"BEGU": true, "CREU": true, "ROSE": true}, "2023-09-03T22Z": {"BEGU": true, "CREU": true, "ROSE": true}, "2023-09-03T23Z": {"BEGU": true, "CREU": true, "ROSE": true}, "2023-09-04T00Z": {"BEGU": true, "CREU": true, "ROSE": true}, "2023-09-04T01Z": {"BEGU": true, "CREU": true, "ROSE": true}, "2023-09-04T02Z": {"BEGU": true, "CREU": true, "ROSE": true}, "2023-09-04T03Z": {"BEGU": true, "CREU": true, "ROSE": true}, "2023-09-04T04Z": {"BEGU": true, "CREU": true, "ROSE": true}, "2023-09-04T05Z": {"BEGU": true, "CREU": true, "ROSE": true}, "2023-09-04T06Z": {"BEGU": true, "CREU": true, "ROSE": true}, "2023-09-04T07Z": {"BEGU": true, "CREU": true, "ROSE": true}, "2023-09-04T08Z": {"BEGU": true}, "2023-08-28T13Z": {"CREU": true, "ROSE": true}}